berye/Berye.py
berye/Column.py
berye/Config.py
berye/Database.py
berye/Table.py
berye/__init__.py
berye-0.7.dist-info/DESCRIPTION.rst
berye-0.7.dist-info/METADATA
berye-0.7.dist-info/RECORD
berye-0.7.dist-info/WHEEL
berye-0.7.dist-info/metadata.json
berye-0.7.dist-info/top_level.txt
