Metadata-Version: 2.0
Name: berye
Version: 0.7
Summary: A library for making the management of our MySQL schema easier for our lambda services
Home-page: https://github.com/tamme-io/berye
Author: tamme
Author-email: opensource@tamme.io
License: MIT
Platform: UNKNOWN
